py_midiplus_fit/Fader.py
py_midiplus_fit/MidiPlus.py
py_midiplus_fit/__init__.py
py_midiplus_fit/__main__.py
py_midiplus_fit-1.1.0.dist-info/LICENSE
py_midiplus_fit-1.1.0.dist-info/METADATA
py_midiplus_fit-1.1.0.dist-info/WHEEL
py_midiplus_fit-1.1.0.dist-info/top_level.txt
py_midiplus_fit-1.1.0.dist-info/RECORD
