Metadata-Version: 2.1
Name: py-midiplus-fit
Version: 1.1.0
Summary: A library for interacting with the MiDiPLUS FIT midi controller.
Home-page: https://github.com/soccermitchy/py_midiplus_fit
Author: Mitchell Monahan
Author-email: pypi@nofla.me
License: UNKNOWN
Platform: UNKNOWN
Classifier: Programming Language :: Python :: 3
Classifier: License :: OSI Approved :: MIT License
Classifier: Operating System :: OS Independent
Requires-Python: >=3.6
Requires-Dist: python-rtmidi
